py_excel_rs-0.6.0.dist-info/METADATA
py_excel_rs-0.6.0.dist-info/WHEEL
py_excel_rs/__init__.py
py_excel_rs/_excel_rs.cpython-310-aarch64-linux-gnu.so
py_excel_rs/df_to_xlsx.py
py_excel_rs/postgres.py
py_excel_rs-0.6.0.dist-info/RECORD
