Metadata-Version: 2.4
Name: py-excel-rs
Version: 0.6.0
Classifier: Programming Language :: Rust
Classifier: Programming Language :: Python :: 3
Classifier: Programming Language :: Python :: 3.8
Classifier: Programming Language :: Python :: 3.9
Classifier: Programming Language :: Python :: 3.10
Classifier: Programming Language :: Python :: 3.11
Classifier: Programming Language :: Python :: 3.12
Classifier: Programming Language :: Python :: 3.13
Classifier: Programming Language :: Python :: Implementation :: CPython
Requires-Dist: pandas
Requires-Dist: numpy
Summary: Some performant utility functions to convert common data structures to XLSX
Requires-Python: >=3.7
